iframes.py
iframes-0.0.7.data/scripts/iframes
iframes-0.0.7.dist-info/METADATA
iframes-0.0.7.dist-info/WHEEL
iframes-0.0.7.dist-info/top_level.txt
iframes-0.0.7.dist-info/RECORD
