Metadata-Version: 2.1
Name: iframes
Version: 0.0.7
Summary: Fast detection of iframes in mpegts streams
Home-page: https://github.com/futzu/iframes
Author: Adrian
Author-email: spam@iodisco.com
Platform: all
Classifier: License :: OSI Approved :: MIT License
Classifier: Operating System :: OS Independent
Classifier: Programming Language :: Python :: 3.6
Classifier: Programming Language :: Python :: Implementation :: PyPy
Classifier: Programming Language :: Python :: Implementation :: CPython
Requires-Python: >=3.6
Requires-Dist: new-reader
